MANIFEST
context_tools.py
setup.cfg
setup.py
test.py
context_tools.egg-info/PKG-INFO
context_tools.egg-info/SOURCES.txt
context_tools.egg-info/dependency_links.txt
context_tools.egg-info/top_level.txt
