Metadata-Version: 1.0
Name: context-tools
Version: 0.2
Summary: Utility functions for context managers
Home-page: http://oakwinter.com/code/context_tools
Author: Collin Winter
Author-email: collinw@gmail.com
License: MIT License
Keywords: context managers decorators generators tests
Platform: UNKNOWN
Classifier: Intended Audience :: Developers
Classifier: License :: OSI Approved :: MIT License
Classifier: Natural Language :: English
Classifier: Operating System :: OS Independent
Classifier: Programming Language :: Python
Classifier: Topic :: Software Development :: Libraries :: Python Modules
